bareos/fuse/__init__.py
bareos/fuse/bareosfuse.py
bareos/fuse/exceptions.py
bareos/fuse/nodefactory.py
bareos/fuse/root.py
bareos/fuse/node/__init__.py
bareos/fuse/node/backups.py
bareos/fuse/node/base.py
bareos/fuse/node/bvfscommon.py
bareos/fuse/node/bvfsdir.py
bareos/fuse/node/bvfsfile.py
bareos/fuse/node/client.py
bareos/fuse/node/clients.py
bareos/fuse/node/directory.py
bareos/fuse/node/file.py
bareos/fuse/node/job.py
bareos/fuse/node/joblog.py
bareos/fuse/node/jobs.py
bareos/fuse/node/jobslist.py
bareos/fuse/node/jobsname.py
bareos/fuse/node/pool.py
bareos/fuse/node/pools.py
bareos/fuse/node/status.py
bareos/fuse/node/volume.py
bareos/fuse/node/volumelist.py
bareos/fuse/node/volumestatus.py
bareos_fuse-0.3.data/scripts/bareos-fuse.py
bareos_fuse-0.3.dist-info/LICENSE
bareos_fuse-0.3.dist-info/METADATA
bareos_fuse-0.3.dist-info/WHEEL
bareos_fuse-0.3.dist-info/top_level.txt
bareos_fuse-0.3.dist-info/RECORD
