Metadata-Version: 2.1
Name: bareos-fuse
Version: 0.3
Summary: Virtual Filesystem showing Bareos information.
Home-page: https://github.com/bareos/bareos-fuse/
Author: Joerg Steffens
Author-email: joerg.steffens@bareos.com
License: AGPLv3
Keywords: bareos fuse filesystem bareosfs
Platform: UNKNOWN
Classifier: Development Status :: 4 - Beta
Classifier: License :: OSI Approved :: GNU Affero General Public License v3
Classifier: Operating System :: POSIX
Classifier: Programming Language :: Python
Classifier: Topic :: System :: Archiving :: Backup
Requires-Dist: fuse-python
Requires-Dist: python-bareos
Requires-Dist: python-dateutil
